maldi_nn/__init__.py
maldi_nn/models.py
maldi_nn/nn.py
maldi_nn/spectrum.py
maldi_nn/reproduce/README.md
maldi_nn/reproduce/__init__.py
maldi_nn/reproduce/amr_baselinescript.py
maldi_nn/reproduce/amr_speciesbaseline.py
maldi_nn/reproduce/clf_baselinescript.py
maldi_nn/reproduce/estimate_peak_distr.py
maldi_nn/reproduce/finetune_amr_hosp.py
maldi_nn/reproduce/modules.py
maldi_nn/reproduce/train_clf_ablate_subsetspecies.py
maldi_nn/scripts/__init__.py
maldi_nn/scripts/domain_adaptation.py
maldi_nn/scripts/process_DRIAMS.py
maldi_nn/scripts/process_RKI.py
maldi_nn/scripts/train_amr.py
maldi_nn/scripts/train_clf.py
maldi_nn/scripts/train_malditransformer.py
maldi_nn/utils/RKI_split.json
maldi_nn/utils/__init__.py
maldi_nn/utils/data.py
maldi_nn/utils/driams_split.json
maldi_nn/utils/drug.py
maldi_nn/utils/hospital_split.json
maldi_nn/utils/metrics.py
maldi_nn/utils/prop.txt
maldi_nn/utils/topf.py
maldi_nn-0.2.5.dist-info/LICENSE
maldi_nn-0.2.5.dist-info/METADATA
maldi_nn-0.2.5.dist-info/WHEEL
maldi_nn-0.2.5.dist-info/entry_points.txt
maldi_nn-0.2.5.dist-info/top_level.txt
maldi_nn-0.2.5.dist-info/RECORD
