Metadata-Version: 2.1
Name: maldi-nn
Version: 0.2.5
Summary: Deep learning tools and models for MALDI-TOF spectra analysis
Home-page: https://github.com/gdewael/maldi-nn
Author: Gaetan De Waele
Requires-Python: >=3.9
License-File: LICENSE
Requires-Dist: numpy
Requires-Dist: torch
Requires-Dist: lightning
Requires-Dist: h5torch >=0.2.5
Requires-Dist: bio-attention
Requires-Dist: pandas
Requires-Dist: scipy
Requires-Dist: matplotlib
Requires-Dist: rdkit
Requires-Dist: selfies
Requires-Dist: deepsmiles
Requires-Dist: scikit-learn
Requires-Dist: xgboost
Requires-Dist: tensorboard
